dvrpsim/__init__.py
dvrpsim/environment.py
dvrpsim/exceptions.py
dvrpsim/model.py
dvrpsim/elements/location.py
dvrpsim/elements/order.py
dvrpsim/elements/vehicle.py
dvrpsim/elements/visit.py
dvrpsim/utils/checker.py
dvrpsim/utils/distances.py
dvrpsim/utils/logging.py
dvrpsim/utils/order_providers.py
dvrpsim/utils/routing.py
dvrpsim/utils/statistics.py
dvrpsim/utils/updaters.py
example_package_hmarkoatsztaki/__init__.py
example_package_hmarkoatsztaki/environment.py
example_package_hmarkoatsztaki/exceptions.py
example_package_hmarkoatsztaki/model.py
example_package_hmarkoatsztaki/elements/checker.py
example_package_hmarkoatsztaki/elements/location.py
example_package_hmarkoatsztaki/elements/order.py
example_package_hmarkoatsztaki/elements/vehicle.py
example_package_hmarkoatsztaki/elements/visit.py
example_package_hmarkoatsztaki/utils/distances.py
example_package_hmarkoatsztaki/utils/logging.py
example_package_hmarkoatsztaki/utils/order_providers.py
example_package_hmarkoatsztaki/utils/routing.py
example_package_hmarkoatsztaki/utils/statistics.py
example_package_hmarkoatsztaki/utils/updaters.py
dvrpsim-1.0.0.dist-info/LICENSE
dvrpsim-1.0.0.dist-info/METADATA
dvrpsim-1.0.0.dist-info/WHEEL
dvrpsim-1.0.0.dist-info/top_level.txt
dvrpsim-1.0.0.dist-info/RECORD
