Metadata-Version: 2.1
Name: dvrpsim
Version: 1.0.0
Summary: A package for modeling and simulating dynamic vehicle routing problems
Author-email: Markó Horváth <marko.horvath@sztaki.hu>, Tímea Tamási <tamasitimea@student.elte.hu>
Project-URL: Homepage, https://github.com/sztaki-hu/dvrpsim
Classifier: Programming Language :: Python :: 3
Classifier: License :: OSI Approved :: MIT License
Classifier: Operating System :: OS Independent
Requires-Python: >=3.8
License-File: LICENSE
Requires-Dist: simpy
